<?xml version="1.0" ?>
<texts base="0xc3d" room_id="68">
    <text>
        <refs>
            <ref>0x3ce</ref>
        </refs>
        <data>Vous êtes les Rebelles,n'est-ce pas?
Personnellement,je crois que vous avez
bonne réputation et un grand coeur.
C'est ça que j'aime![end][end]</data>
    </text>
    <text>
        <refs>
            <ref>0x38c</ref>
        </refs>
        <data>Il y a une personne qui dort,
ne fais pas de bruit.[end]</data>
    </text>
    <text>
        <refs>
            <ref>0x764</ref>
        </refs>
        <data>DON JUAN:
Mon dieu,cette ravissante jeune femme
est malade.[end]</data>
    </text>
    <text>
        <refs>
            <ref>0x3c5</ref>
        </refs>
        <data>Il y a,dans cette ville,de nombreux
Petits Démons qui sont libres.
Ils pourraient vous aider?[end]</data>
    </text>
    <text>
        <refs>
            <ref>0x5f4</ref>
        </refs>
        <data>DON JUAN:
Grâce à votre flamme,
j'ai le coeur chaud.
Vous êtes pour moi une jeune personne
venue tout droit du ciel.[end]</data>
    </text>
    <text>
        <refs>
            <ref>0x5fa</ref>
        </refs>
        <data>Le saviez-vous?[end]</data>
    </text>
    <text>
        <refs>
            <ref>0x608</ref>
        </refs>
        <data>Ah?!
Mais qui êtes-vous?![end]</data>
    </text>
    <text>
        <refs>
            <ref>0x612</ref>
        </refs>
        <data>DON JUAN:
Mais je suis Don Juan qui a d'énormes
sentiments pour vous![end]</data>
    </text>
    <text>
        <refs>
            <ref>0x618</ref>
        </refs>
        <data>Haha...[end]</data>
    </text>
    <text>
        <refs>
            <ref>0x628</ref>
        </refs>
        <data>DON JUAN:
Moi,Don Juan,je vous aime.
J'ai un grand coeur.[end]</data>
    </text>
    <text>
        <refs>
            <ref>0x634</ref>
        </refs>
        <data>Vous avez un coeur pur mais il est si
seul... si solitaire![end]</data>
    </text>
    <text>
        <refs>
            <ref>0x642</ref>
        </refs>
        <data>Vous ne le pensez pas?[end]</data>
    </text>
    <text>
        <refs>
            <ref>0x650</ref>
        </refs>
        <data>Si j'observais votre coeur dans un
microscope,je verrais que j'y suis
présent.[end]</data>
    </text>
    <text>
        <refs>
            <ref>0x659</ref>
        </refs>
        <data>Cependant j'y vois aussi que vous
manquez d'audace.[end]</data>
    </text>
    <text>
        <refs>
            <ref>0x669</ref>
        </refs>
        <data>DON JUAN:
Etc etc etc...[end]</data>
    </text>
    <text>
        <refs>
            <ref>0x697</ref>
        </refs>
        <data>LUKIA:
Don Juan!
Que fais-tu?[end]</data>
    </text>
    <text>
        <refs>
            <ref>0x8ac</ref>
            <ref>0x6af</ref>
        </refs>
        <data>DON JUAN:
Hein?!
Oh,pardonne-moi Lukia![end]</data>
    </text>
    <text>
        <refs>
            <ref>0x703</ref>
        </refs>
        <data>Dans ce lit se trouve une personne
venant de Kana.[end]</data>
    </text>
    <text>
        <refs>
            <ref>0x70d</ref>
        </refs>
        <data>[character][0x0]...
Est-ce que je cauchemarde?[end]</data>
    </text>
    <text>
        <refs>
            <ref>0x71b</ref>
        </refs>
        <data>MIST:
[character][0x0]?[end]</data>
    </text>
    <text>
        <refs>
            <ref>0x721</ref>
        </refs>
        <data>Est-ce toi,[character][0x0]?![end]</data>
    </text>
    <text>
        <refs>
            <ref>0x72a</ref>
        </refs>
        <data>C'est moi... Mist...
Une cavalière de Kana![end]</data>
    </text>
    <text>
        <refs>
            <ref>0x734</ref>
        </refs>
        <data>Tu ne me reconnais pas?[end]</data>
    </text>
    <text>
        <refs>
            <ref>0x7b4</ref>
        </refs>
        <data>MATELIGHT:
Mi... Mist!
Tu es encore en vie?![end]</data>
    </text>
    <text>
        <refs>
            <ref>0x7c2</ref>
        </refs>
        <data>MIST:
Capitaine Matelight!
 
Nous ne nous étions plus vus depuis
la malheureuse chute de Kana.[end]</data>
    </text>
    <text>
        <refs>
            <ref>0x7e7</ref>
        </refs>
        <data>MATELIGHT:
Hoho!
 
Je croyais vraiment que je ne te
reverrais plus.
 
Mais au fait,comment as-tu réussi à
fuir Kana?[end]</data>
    </text>
    <text>
        <refs>
            <ref>0x7f5</ref>
        </refs>
        <data>Une minute!
Ta voix...
C'est celle d'une malade![end]</data>
    </text>
    <text>
        <refs>
            <ref>0x7fe</ref>
        </refs>
        <data>MATELIGHT:
Est-ce que tu vas bien?[end]</data>
    </text>
    <text>
        <refs>
            <ref>0x80b</ref>
        </refs>
        <data>MIST:
Hum...
Tout va bien...
J'ai tout de suite repris des forces
en voyant le visage du Capitaine
[character][0x0]![end]</data>
    </text>
    <text>
        <refs>
            <ref>0x819</ref>
        </refs>
        <data>MATELIGHT:
Si tu le dis!
 
[character][0x0] doit sûrement t'illuminer de
bonheur![end]</data>
    </text>
    <text>
        <refs>
            <ref>0x823</ref>
        </refs>
        <data>MIST:
Il est temps pour moi de revenir avec
vous.[end]</data>
    </text>
    <text>
        <refs>
            <ref>0x82d</ref>
        </refs>
        <data>J'ai été aidée par un homme et je
dois vous aider.[end]</data>
    </text>
    <text>
        <refs>
            <ref>0x83b</ref>
        </refs>
        <data>MATELIGHT:
Quoi?!
Par qui?![end]</data>
    </text>
    <text>
        <refs>
            <ref>0x841</ref>
        </refs>
        <data>MIST:
... ... ... ...[end]</data>
    </text>
    <text>
        <refs>
            <ref>0x84f</ref>
        </refs>
        <data>MATELIGHT:
Mist,qui t'a aidé à t'enfuir de Kana?[end]</data>
    </text>
    <text>
        <refs>
            <ref>0x855</ref>
        </refs>
        <data>MIST:
Un Général de Granbelos...
Le Grand Palpaleos![end]</data>
    </text>
    <text>
        <refs>
            <ref>0x863</ref>
        </refs>
        <data>MATELIGHT:
Palpaleos?![end]</data>
    </text>
    <text>
        <refs>
            <ref>0x86f</ref>
        </refs>
        <data>DON JUAN:
Un Général de l'Empire aidant une
cavalière de Kana?[end]</data>
    </text>
    <text>
        <refs>
            <ref>0x880</ref>
        </refs>
        <data>MIST:
Je n'ai toujours pas compris ce qui
l'a poussé à m'aider.[end]</data>
    </text>
    <text>
        <refs>
            <ref>0x89a</ref>
        </refs>
        <data>LUKIA:
[character][0x0]!
Mélodia t'attend![end][end]</data>
    </text>
    <text>
        <refs>
            <ref>0x919</ref>
        </refs>
        <data>WAGAHAI:
[0xa8]wagahai aller sur le bateau!
 mort transporter sur bateau!
 là-bas fait sombre...[0xa9][end]</data>
    </text>
    <text>
        <refs>
            <ref>0x2d7</ref>
        </refs>
        <data>DON JUAN:
Si tu regardes Lukia,tu verras qu'elle
pense que Don Juan est un héros.[end][end]</data>
    </text>
    <text>
        <refs>
            <ref>0x96c</ref>
        </refs>
        <data>MELODIA:
C'est mon grand-père![end]</data>
    </text>
    <text>
        <refs>
            <ref>0x97d</ref>
        </refs>
        <data>GRAND-PERE:
Hoho!
Ne serais-tu pas [character][0x0]?
Mélodia m'a énormément parlé de toi
et de tes exploits.[end]</data>
    </text>
    <text>
        <refs>
            <ref>0x987</ref>
        </refs>
        <data>Tout comme ma petite-fille,j'aime
parler et je suis un très bon conteur.[end]</data>
    </text>
    <text>
        <refs>
            <ref>0x995</ref>
        </refs>
        <data>MELODIA:
Grand-père,racontes-nous une histoire!
S'il te plaît!
Viiite![end]</data>
    </text>
    <text>
        <refs>
            <ref>0x9a3</ref>
        </refs>
        <data>GRAND-PERE:
Tu es bien impatiente Mélodia!
Bon,je vais vous en raconter une.[end]</data>
    </text>
    <text>
        <refs>
            <ref>0x9a9</ref>
        </refs>
        <data>MELODIA:
Est-ce que tu pourrais me dire le sens
de mon prénom?[end]</data>
    </text>
    <text>
        <refs>
            <ref>0x9b3</ref>
        </refs>
        <data>GRAND-PERE:
Hohoho! Cela s'est toujours transmis
à Godrand.[end]</data>
    </text>
    <text>
        <refs>
            <ref>0x9f6</ref>
        </refs>
        <data>Tu seras toujours à Godrand la
bienvenue mais aujourd'hui je suis
occupée.[end]</data>
    </text>
    <text>
        <refs>
            <ref>0xa09</ref>
        </refs>
        <data>Je suis aujourd'hui revenue mais ce
n'est que pour un instant.[end]</data>
    </text>
    <text>
        <refs>
            <ref>0xa1c</ref>
        </refs>
        <data>Je suis rapidement revenue car je
m'inquiétais beaucoup.[end]</data>
    </text>
    <text>
        <refs>
            <ref>0xa2f</ref>
        </refs>
        <data>Pardonnez mon impatience mais je dois
repartir pour ensuite revenir![end]</data>
    </text>
    <text>
        <refs>
            <ref>0xa69</ref>
        </refs>
        <data>Voici le sens de ton prénom!
Tout le monde a compris?[end]</data>
    </text>
    <text>
        <refs>
            <ref>0xa6f</ref>
        </refs>
        <data>MELODIA:
Grand-père!
Ce ne sont que de vieux proverbes.
Tu n'as fait que changer le nom de
la personne à qui ils s'appliquent!
C'est trop facile![end]</data>
    </text>
    <text>
        <refs>
            <ref>0xa7d</ref>
        </refs>
        <data>GRAND-PERE:
Autrefois,nombreux étaient les gens qui
adoraient la magie des Petits Démons.[end]</data>
    </text>
    <text>
        <refs>
            <ref>0xa83</ref>
        </refs>
        <data>Je t'avais dit qu'il y avait des Petits
Démons et des dragons à Kana.
 
C'est pour cette raison que tu es
montée sur un dragon pour aller en
direction de Kana.
J'ignorais qu'un jour,
tu reviendrais ici.[end]</data>
    </text>
    <text>
        <refs>
            <ref>0xaa2</ref>
        </refs>
        <data>MELODIA:
Grand-père,je te félicite![end]</data>
    </text>
    <text>
        <refs>
            <ref>0xaa8</ref>
        </refs>
        <data>Je crois que notre famille est née
pour voyager.[end]</data>
    </text>
    <text>
        <refs>
            <ref>0xab6</ref>
        </refs>
        <data>GRAND-PERE:
Haha!
 
A chaque fois qu'on voyage,
j'ai le sang qui remue.
 
Et dès que nous revenons,
je redeviens une autre personne.[end]</data>
    </text>
    <text>
        <refs>
            <ref>0xace</ref>
        </refs>
        <data>MELODIA:
[character][0x0]![end]</data>
    </text>
    <text>
        <refs>
            <ref>0xadc</ref>
        </refs>
        <data>C'est grâce à ces voyages que
grand-père dit et transmet de
nombreux proverbes à Godrand.
Si tu veux,il peut t'en dire encore
beaucoup![end]</data>
    </text>
    <text>
        <refs>
            <ref>0xb10</ref>
        </refs>
        <data>GRAND-PERE:
Hoho!
N'exagère pas!
Mais il est vrai que j'en connais un
d'une très grande importance.[end]</data>
    </text>
    <text>
        <refs>
            <ref>0xb23</ref>
        </refs>
        <data>Il provient d'une très vieille légende
de Godrand...[end]</data>
    </text>
    <text>
        <refs>
            <ref>0xb35</ref>
        </refs>
        <data>Un Dragon à l'apparence d'un oiseau
dort dans cette région.[end]</data>
    </text>
    <text>
        <refs>
            <ref>0xb39</ref>
        </refs>
        <data>Lorsqu'il sera débordant de colère,
le Dragon Oiseau s'éveillera.[end][end]</data>
    </text>
    <text>
        <refs>
            <ref>0xb51</ref>
        </refs>
        <data>SENDACK:
Une Légende de Dragon Sacré?[end]</data>
    </text>
    <text>
        <refs>
            <ref>0xb5a</ref>
        </refs>
        <data>[character][0x1]:
Le Dragon Oiseau...
C'est Garuda!
Il est furieux...
Je sens sa terrible colère...[end]</data>
    </text>
    <text>
        <refs>
            <ref>0xb66</ref>
        </refs>
        <data>SENDACK:
Je sens aussi quelque chose...[end]</data>
    </text>
    <text>
        <refs>
            <ref>0xb7a</ref>
        </refs>
        <data>[character][0x1]:
Savez-vous où se trouve le lieu de
repos de Garuda?[end]</data>
    </text>
    <text>
        <refs>
            <ref>0xb84</ref>
        </refs>
        <data>GRAND-PERE:
Je l'ai même déjà vu et il se trouve
à l'Ouest d'ici.
Pensez au bon esprit car la magie peut
tout vaincre.[end]</data>
    </text>
    <text>
        <refs>
            <ref>0x3e0</ref>
        </refs>
        <data>Tu as déjà vu un microscope?
Tu as déjà regardé dedans?[end]</data>
    </text>
    <text>
        <refs>
            <ref>0x2d0</ref>
        </refs>
        <data>LUKIA:
Moi et lui? Ensemble?!
Jamais!
Don Juan ne cesse d'importuner les
femmes![end]</data>
    </text>
    <text>
        <refs>
            <ref>0x2e2</ref>
        </refs>
        <data>Hum...[end]</data>
    </text>
    <text>
        <refs>
            <ref>0x393</ref>
        </refs>
        <data>Vous êtes l'un des amis de cette
personne?
Vous pouvez aller la voir![end]</data>
    </text>
    <text>
        <refs>
            <ref>0x3e7</ref>
        </refs>
        <data>Est-ce que tu es [character][0x0]?[end]</data>
    </text>
    <text>
        <refs>
            <ref>0x2e9</ref>
        </refs>
        <data>MIST:
Un jour,j'espère que mon souhait se
réalisera...
Je n'abandonnerai jamais...[end]</data>
    </text>
    <text>
        <refs>
            <ref>0x2b7</ref>
        </refs>
        <data>MATELIGHT:
Maintenant,toute la cavalerie de Kana
est restaurée![end]</data>
    </text>
    <text>
        <refs>
            <ref>0x296</ref>
        </refs>
        <data>SENDACK:
[character][0x0]...
Je... je...
 [0xa8]Il dit des inepties...[0xa9]
 [0xa8]Et il se répète en plus...[0xa9][end]</data>
    </text>
    <text>
        <refs>
            <ref>0x2ad</ref>
        </refs>
        <data>MATELIGHT:
Hoho [character][0x0]!
 
Il y a longtemps,ici,
il y avait plein de Petits Démons.
 
Ils dansent souvent quand ils sont
ensembles.[end]</data>
    </text>
    <text>
        <refs>
            <ref>0x2c2</ref>
        </refs>
        <data>COMMANDANT:
J'apprécie ce que tu fais![end]</data>
    </text>
    <text>
        <refs>
            <ref>0x29f</ref>
        </refs>
        <data>SENDACK:
[0xa8]Il dit des inepties.[0xa9]
[0xa8]C'est lassant,il se répète.[0xa9][end]</data>
    </text>
    <text>
        <refs>
            <ref>0x2c9</ref>
        </refs>
        <data>COMMANDANT:
Un chevalier ne doit pas boire d'alcool
au bar![end]</data>
    </text>
    <text>
        <refs>
            <ref>0x2f6</ref>
        </refs>
        <data>C'est un peu petit,ici!
Vous ne voudriez pas quelques armes?[end]</data>
    </text>
    <text>
        <refs>
            <ref>0x326</ref>
        </refs>
        <data>Nous sommes un peu à l'étroit.
Vous aimeriez des armures?[end]</data>
    </text>
    <text>
        <refs>
            <ref>0x356</ref>
        </refs>
        <data>On étouffe ici.
Vous aimeriez faire des affaires?[end]</data>
    </text>
    <text>
        <refs>
            <ref>0x2fa</ref>
            <ref>0x32a</ref>
            <ref>0x35a</ref>
        </refs>
        <data> Acheter.
 Je suis occupé.[end1]</data>
    </text>
    <text>
        <refs>
            <ref>0x422</ref>
        </refs>
        <data>Merci beaucoup.[end]</data>
    </text>
    <text>
        <refs>
            <ref>0x42e</ref>
        </refs>
        <data>Il y avait beaucoup de Petits Démons
dans cette ville.
 
Qu'est-ce que la mort sacrée?!
 
  
Cela signifie qu'ils ont choisi une
personne et qu'ils la protègeront
pour toujours.[end]</data>
    </text>
    <text>
        <refs>
            <ref>0x3d9</ref>
        </refs>
        <data>Ici,Godrand est en paix mais à
l'extérieur,c'est terrible.[end]</data>
    </text>
    <text>
        <refs>
            <ref>0xb92</ref>
        </refs>
        <data>MELODIA:
Nous devons aller dans cette grotte!
Je vais appeler les dragons![end]</data>
    </text>
    <text>
        <refs>
            <ref>0x3be</ref>
        </refs>
        <data>J'adore les Rebelles.
Les combats que mène l'Empire sont
trop terribles![end]</data>
    </text>
    <text>
        <refs>
            <ref>0x28b</ref>
        </refs>
        <data>[character][0x1]:
Sendack a encore trop bu d'alcool...[end]</data>
    </text>
    <text>
        <refs>
            <ref>0x49c</ref>
        </refs>
        <data>Obtenu [0xaa]ARMURE FURTIVE[0xab].[end]</data>
    </text>
    <text>
        <refs>
            <ref>0x4ad</ref>
        </refs>
        <data>Obtenu [0xb6] [0xaa]POEME[0xab].[end]</data>
    </text>
    <text>
        <refs>
            <ref>0x4c5</ref>
        </refs>
        <data>Obtenu [0xaa]HERBE SACRE[0xab].[end]</data>
    </text>
    <text>
        <refs>
            <ref>0x4d9</ref>
        </refs>
        <data>Obtenu [0xaa]ASSAUT[0xab].[end]</data>
    </text>
    <text>
        <refs>
            <ref>0x4ea</ref>
        </refs>
        <data>Obtenu [0xaa]BATON MAITRE[0xab].[end]</data>
    </text>
    <text>
        <refs>
            <ref>0x4fb</ref>
        </refs>
        <data>Obtenu [0xaa]MEMOIRE MAUVAISE[0xab].[end]</data>
    </text>
    <text>
        <refs>
            <ref>0x50c</ref>
        </refs>
        <data>Obtenu [0xaa]ELIXIR[0xab].[end]</data>
    </text>
    <text>
        <refs>
            <ref>0xbb7</ref>
        </refs>
        <data>SENDACK:
Allons-y...[end]</data>
    </text>
</texts>
